code_pruner/__init__.py
code_pruner/demo.py
code_pruner/prune.py
code_pruner/utils.py
code_pruner/metadata/__init__.py
code_pruner/metadata/path_provider.py
code_pruner/metadata/rules_provider.py
code_pruner/pruning/__init__.py
code_pruner/pruning/data_types.py
code_pruner/pruning/macher.py
code_pruner/pruning/transformers.py
code_pruner-0.5.7.dist-info/LICENSE.md
code_pruner-0.5.7.dist-info/METADATA
code_pruner-0.5.7.dist-info/WHEEL
code_pruner-0.5.7.dist-info/top_level.txt
code_pruner-0.5.7.dist-info/RECORD
