Metadata-Version: 2.1
Name: code-pruner
Version: 0.5.7
Summary: A tool to prune Python code based on specified patterns.
Home-page: UNKNOWN
Author: liubomyr.ivanitskyi
Author-email: lubomyr.ivanitskiy@gmail.com
License: MIT License
Platform: UNKNOWN
License-File: LICENSE.md
Requires-Dist: libcst
Requires-Dist: pathspec
Requires-Dist: typing-extensions
Requires-Dist: argumentize
